sslib/__init__.py
sslib/randomness.py
sslib/util.py
sslib/shamir/__init__.py
sslib/shamir/shamir.py
sslib-0.2.0.dist-info/DESCRIPTION.rst
sslib-0.2.0.dist-info/METADATA
sslib-0.2.0.dist-info/RECORD
sslib-0.2.0.dist-info/WHEEL
sslib-0.2.0.dist-info/metadata.json
sslib-0.2.0.dist-info/top_level.txt
