Metadata-Version: 1.2
Name: sslib
Version: 0.2.0
Summary: A Python3 library for sharing secrets.
Home-page: https://github.com/jqueiroz/python-sslib
Author: Jonathan Queiroz
Author-email: dev@johnjq.com
License: MIT
Platform: UNKNOWN
Requires-Python: >=3
